<?xml version="1.0" encoding="UTF-8"?>
<sv:node xmlns:sv="http://www.jcp.org/jcr/sv/1.0" xmlns:xsi="http://www.w3.org/2001/XMLSchema-instance" sv:name="bls">
  <sv:property sv:name="jcr:primaryType" sv:type="Name">
    <sv:value>mgnl:contentNode</sv:value>
  </sv:property>
  <sv:property sv:name="color" sv:type="String">
    <sv:value>#23833B</sv:value>
  </sv:property>
  <sv:property sv:name="label" sv:type="String">
    <sv:value>BLS</sv:value>
  </sv:property>
  <sv:property sv:name="permanent" sv:type="String">
    <sv:value>true</sv:value>
  </sv:property>
  <sv:node sv:name="apps">
    <sv:property sv:name="jcr:primaryType" sv:type="Name">
      <sv:value>mgnl:contentNode</sv:value>
    </sv:property>
    <sv:node sv:name="haltestellen">
      <sv:property sv:name="jcr:primaryType" sv:type="Name">
        <sv:value>mgnl:contentNode</sv:value>
      </sv:property>
    </sv:node>
    <sv:node sv:name="wagentypen">
      <sv:property sv:name="jcr:primaryType" sv:type="Name">
        <sv:value>mgnl:contentNode</sv:value>
      </sv:property>
    </sv:node>
    <sv:node sv:name="wagenplaene">
      <sv:property sv:name="jcr:primaryType" sv:type="Name">
        <sv:value>mgnl:contentNode</sv:value>
      </sv:property>
    </sv:node>
    <sv:node sv:name="waegen">
      <sv:property sv:name="jcr:primaryType" sv:type="Name">
        <sv:value>mgnl:contentNode</sv:value>
      </sv:property>
    </sv:node>
    <sv:node sv:name="strecken">
      <sv:property sv:name="jcr:primaryType" sv:type="Name">
        <sv:value>mgnl:contentNode</sv:value>
      </sv:property>
    </sv:node>
    <sv:node sv:name="zugkompositionen">
      <sv:property sv:name="jcr:primaryType" sv:type="Name">
        <sv:value>mgnl:contentNode</sv:value>
      </sv:property>
    </sv:node>
    <sv:node sv:name="zugservices">
      <sv:property sv:name="jcr:primaryType" sv:type="Name">
        <sv:value>mgnl:contentNode</sv:value>
      </sv:property>
    </sv:node>
    <sv:node sv:name="reservationen">
      <sv:property sv:name="jcr:primaryType" sv:type="Name">
        <sv:value>mgnl:contentNode</sv:value>
      </sv:property>
    </sv:node>
  </sv:node>
</sv:node>

